{"lang": {
    "guardian": "Guardián",
    "seeker": "Buscador",
    "rogue": "Rebelde",
    "mystic": "Místico",
    "survivor": "Superviviente",
    "neutral": "Neutral",
    "multiclass": "Multiclase",
    "permanent": "Permanente",
    "exceptional": "Excepcional",
    "advanced/parallel": "Avanzada/Paralela",
    "unique": "Única",
    "signature": "Característica",
    "scenario": "Escenario",
    "parallel": "Paralelo/a",
    "cost": "Coste",
    "act": "Acto",
    "agenda": "Plan",
    "clues": "Pistas",
    "shroud": "Velo",
    "treachery": "Traición",
    "enemy": "Enemigo",
    "location": "Lugar",
    "player_cards": "Cartas de Jugador",
    "xp": "Experiencia",
    "mythos": "Mitos",
    "attack": "Ataque",
    "vengeance": "Venganza",
    "victory": "Victoria",
    "assets_hand": "Mano",
    "assets_hand2": "Mano x2",
    "assets_body": "Cuerpo",
    "assets_accessory": "Accesorio",
    "assets_arcane": "Arcano",
    "assets_arcane2": "Arcano x2",
    "assets_ally": "Aliado",
    "assets_others": "Otros",
    "assets_permanents": "Permanentes",
    "investigator": "Investigador",
    "xp_needed": "Experiencia necesaria",
    "xp_upgrade": "Experiencia (necesaria/obtenida)",
    "assets": "Apoyos",
    "events": "Eventos",
    "skills": "Habilidades",
    "treacheries/enemies": "Traiciones/Enemigos",
    "added_cards": "Cartas añadidas",
    "removed_cards": "Cartas retiradas",
    "upgraded_cuz_cards": "Cartas Personalizables mejoradas",
    "deck_not_found": "El Mazo no fue encontrado.",
    "upgrade_not_found": "Mejora de mazo no fue encontrada.",
    "card_not_found": "La carta no fue encontrada.",
    "ahWho_card_not_found": "La carta no fue encontrada o era una carta sin nivel (característica, debilidad, enlazada, etc.)",
    "errata_title": "Errata",
    "faq_title": "Preguntas Frecuentes",
    "faq_not_found": "No hay FAQ con esta carta (aún)",
    "taboo_title": "Taboo más reciente",
    "taboo_chained": "Encadenada",
    "taboo_unchained": "Desencadenada",
    "ah_description": "Busca cartas de jugador en ArkhamDB.",
    "ahDeck_description": "Busca mazos de jugador en ArkhamDB.",
    "ahUp_description": "Busca mejoras de mazos de jugador en ArkhamDB.",
    "ahe_description": "Busca cartas de encuentros en ArkhamDB.",
    "ahb_description": "Busca cartas traseras en ArkhamDB.",
    "ahTarot_description": "Busca cartas (o al azar) de Tarot del Regreso al Circulo Roto.",
    "ahTiming_description": "Muestra la estructura de las fases del juego o de una prueba de habilidad.",
    "ahRandom_description": "Devuelve una carta de jugador que no es de historia al azar dado los parámetros dados.",
    "ahList_description": "Devuelve hasta 20 cartas de jugador que no son de historia que cumplen los parámetros dados.",
    "ahWho_description": "Devuelve una lista de los Investigadores que pueden llevar la carta en su mazo.",
    "ahCustomizable_description": "Busca la lista de mejoras de una carta Personalizable.",
    "customization_note": "(Para ver las opciones de mejoras disponibles usa el comando /ahCustomizable )",
    "ahWho_title": "¿Quien puede llevar esta carta?",
    "ahWho_title_neg": "¿Quien NO puede llevar esta carta?",
    "ahWho_neg_text": "Casi todos los Investigadores pueden llevar esta carta, excepto:",
    "ahWho_versatile_text": "Nota: Esta lista no considera el uso de Versátil (Devoradores de Sueños #167)",
    "ahWho_everyone": "Cualquier investigador/a puede llevar esta carta! (Por ahora)",
    "name_description": "Nombre de la carta",
    "trait_description": "Rasgo(s) de la carta, puedes incluir más de uno separando por comas. (ej: Aliado, Viajero)",
    "level_description": "Nivel de la carta",
    "faction_description": "Clase de la carta",
    "sub_description": "Subtítulo de la carta",
    "pack_description": "Nombre del ciclo de la carta",
    "text_description": "Texto de Reglas Impreso (para símbolos hazlo así: [auto_fail])",
    "deck_code_desc": "Código del mazo en ArkhamDB",
    "deck_type_desc": "Tipo de Mazo (deck o decklist)",
    "public_deck": "Público",
    "private_deck": "Privado",
    "card_type_desc": "Tipo de Carta",
    "extras_description": "Extras",
    "tarot_title": "Carta de Tarot",
    "tarot_up_name": "Normal",
    "tarot_down_name": "Invertido",
    "tarot_orientation": "Orientation robada",
    "timings_type_desc": "Secuencia de la Fase del juego o de una prueba de habilidad.",
    "mythos_phase": "Fase de Mitos",
    "investigation_phase": "Fase de Investigación",
    "enemy_phase": "Fase de Enemigos",
    "upkeep_phase": "Fase de Mantenimiento",
    "skill_test": "Resolución de prueba de habilidad",
    "self_delete": "Eliminar",
    "ahList_title": "Cartas encontradas:",
    "ahPreview_description": "Busca cartas que aún no han salido, cartas beta, etc.",
    "customization_title": "Mejoras Disponibles:",
    "preview_set": "Esta es una carta beta/avance"
    }
}
